app_cronjob/__init__.py
app_cronjob/cronjob.py
app_cronjob-1.0.0.dist-info/METADATA
app_cronjob-1.0.0.dist-info/WHEEL
app_cronjob-1.0.0.dist-info/entry_points.txt
app_cronjob-1.0.0.dist-info/top_level.txt
app_cronjob-1.0.0.dist-info/RECORD
